demyst/__init__.py
demyst/__main__.py
demyst/cli.py
demyst/console.py
demyst/exceptions.py
demyst/fixer.py
demyst/lazy.py
demyst/magic.py
demyst/main.py
demyst/mcp.py
demyst/plugins.py
demyst/red_team.py
demyst/security.py
demyst/utils.py
demyst/watchdog.py
demyst/config/__init__.py
demyst/config/manager.py
demyst/config/models.py
demyst/engine/__init__.py
demyst/engine/cst_transformer.py
demyst/engine/mirage_detector.py
demyst/engine/parallel.py
demyst/engine/suppression.py
demyst/engine/transpiler.py
demyst/engine/variation_tensor.py
demyst/engine/variation_transformer.py
demyst/generators/__init__.py
demyst/generators/paper_generator.py
demyst/generators/report_generator.py
demyst/guards/__init__.py
demyst/guards/hypothesis_guard.py
demyst/guards/leakage_hunter.py
demyst/guards/tensor_guard.py
demyst/guards/unit_guard.py
demyst/integrations/__init__.py
demyst/integrations/ci_enforcer.py
demyst/integrations/experiment_trackers.py
demyst/integrations/jax_hooks.py
demyst/integrations/torch_hooks.py
demyst/profiles/__init__.py
demyst/profiles/base.py
demyst/profiles/biology.py
demyst/profiles/climate.py
demyst/profiles/economics.py
demyst/profiles/neuroscience.py
demyst/profiles/physics.py
demyst/tests/__init__.py
demyst/tests/conftest.py
demyst/tests/test_agent_loop.py
demyst/tests/test_cli.py
demyst/tests/test_cli_output.py
demyst/tests/test_commit_review.py
demyst/tests/test_demyst_system.py
demyst/tests/test_edge_cases.py
demyst/tests/test_examples_hypothesis.py
demyst/tests/test_examples_leakage.py
demyst/tests/test_examples_mirage.py
demyst/tests/test_examples_tensor.py
demyst/tests/test_examples_units.py
demyst/tests/test_fixes_verification.py
demyst/tests/test_generators.py
demyst/tests/test_guards.py
demyst/tests/test_infra_coverage.py
demyst/tests/test_integrations.py
demyst/tests/test_magic.py
demyst/tests/test_mcp.py
demyst/tests/test_property_based.py
demyst/tests/test_security.py
demyst/tests/test_swarm_collapse.py
demyst/tests/test_target.py
demyst-0.1.0a2.dist-info/licenses/LICENSE
demyst-0.1.0a2.dist-info/METADATA
demyst-0.1.0a2.dist-info/WHEEL
demyst-0.1.0a2.dist-info/entry_points.txt
demyst-0.1.0a2.dist-info/top_level.txt
demyst-0.1.0a2.dist-info/RECORD
