Metadata-Version: 2.4
Name: demyst
Version: 0.1.0a2
Summary: Scientific integrity linter for academic code
Home-page: https://github.com/Hmbown/demyst
Author: Demyst Team
Author-email: Hunter Brown <hunter@demyst.dev>
License: MIT
Project-URL: Homepage, https://github.com/Hmbown/demyst
Project-URL: Documentation, https://github.com/Hmbown/demyst#readme
Project-URL: Repository, https://github.com/Hmbown/demyst
Project-URL: Issues, https://github.com/Hmbown/demyst/issues
Keywords: linting,scientific-computing,machine-learning,data-science,integrity,reproducibility,p-hacking,data-leakage,mirage,computational-mirages
Classifier: Development Status :: 3 - Alpha
Classifier: Intended Audience :: Science/Research
Classifier: Intended Audience :: Developers
Classifier: License :: OSI Approved :: MIT License
Classifier: Operating System :: OS Independent
Classifier: Programming Language :: Python :: 3
Classifier: Programming Language :: Python :: 3.8
Classifier: Programming Language :: Python :: 3.9
Classifier: Programming Language :: Python :: 3.10
Classifier: Programming Language :: Python :: 3.11
Classifier: Programming Language :: Python :: 3.12
Classifier: Topic :: Scientific/Engineering :: Artificial Intelligence
Classifier: Topic :: Software Development :: Quality Assurance
Requires-Python: >=3.8
License-File: LICENSE
Requires-Dist: numpy>=1.20.0
Requires-Dist: PyYAML>=6.0
Requires-Dist: pydantic>=2.0.0
Requires-Dist: libcst>=1.0.0
Requires-Dist: rich>=13.0.0
Requires-Dist: langchain-core>=0.1.0
Requires-Dist: mcp>=1.0.0; python_version >= "3.10"
Requires-Dist: ipython>=8.0.0
Requires-Dist: scipy>=1.7.0
Provides-Extra: torch
Requires-Dist: torch>=1.9.0; extra == "torch"
Provides-Extra: jax
Requires-Dist: jax>=0.3.0; extra == "jax"
Requires-Dist: jaxlib>=0.3.0; extra == "jax"
Provides-Extra: tracking
Requires-Dist: wandb>=0.12.0; extra == "tracking"
Requires-Dist: mlflow>=1.20.0; extra == "tracking"
Provides-Extra: all
Requires-Dist: torch>=1.9.0; extra == "all"
Requires-Dist: jax>=0.3.0; extra == "all"
Requires-Dist: jaxlib>=0.3.0; extra == "all"
Requires-Dist: wandb>=0.12.0; extra == "all"
Requires-Dist: mlflow>=1.20.0; extra == "all"
Provides-Extra: dev
Requires-Dist: pytest>=6.0.0; extra == "dev"
Requires-Dist: pytest-cov>=2.0.0; extra == "dev"
Requires-Dist: mypy>=1.0.0; extra == "dev"
Requires-Dist: black>=23.0.0; extra == "dev"
Requires-Dist: isort>=5.0.0; extra == "dev"
Requires-Dist: pre-commit>=3.0.0; extra == "dev"
Requires-Dist: hypothesis>=6.0.0; extra == "dev"
Requires-Dist: mutmut>=2.0.0; extra == "dev"
Requires-Dist: scipy>=1.7.0; extra == "dev"
Requires-Dist: pandas>=1.3.0; extra == "dev"
Requires-Dist: scikit-learn>=1.0.0; extra == "dev"
Dynamic: author
Dynamic: home-page
Dynamic: license-file
Dynamic: requires-python
